Metadata-Version: 2.1
Name: fastapi-redis-cache-reborn
Version: 0.3.1
Summary: A simple and robust caching solution for FastAPI endpoints using Redis.
Home-page: https://github.com/seapagan/fastapi-redis-cache-reborn
License: MIT
Author: Grant Ramsay
Author-email: seapagan@gmail.com
Requires-Python: >=3.9,<4.0
Classifier: Development Status :: 4 - Beta
Classifier: Framework :: FastAPI
Classifier: Intended Audience :: Developers
Classifier: License :: OSI Approved :: MIT License
Classifier: Natural Language :: English
Classifier: Operating System :: OS Independent
Classifier: Programming Language :: Python :: 3
Classifier: Programming Language :: Python :: 3.9
Classifier: Programming Language :: Python :: 3.10
Classifier: Programming Language :: Python :: 3.11
Classifier: Programming Language :: Python :: 3.12
Classifier: Programming Language :: Python :: 3 :: Only
Classifier: Topic :: Software Development :: Libraries :: Python Modules
Requires-Dist: fastapi[all] (>=0.110.2,<0.112.0)
Requires-Dist: pydantic (>=2.7.1,<3.0.0)
Requires-Dist: redis (>=5.0.4,<6.0.0)
Requires-Dist: tzlocal (>=5.2,<6.0)
Project-URL: Bug Tracker, https://github.com/seapagan/fastapi-redis-cache-reborn/issues
Project-URL: Documentation, https://seapagan.github.io/fastapi-redis-cache-reborn/
Project-URL: Pull Requests, https://github.com/seapagan/fastapi-redis-cache-reborn/pulls
Project-URL: Repository, https://github.com/seapagan/fastapi-redis-cache-reborn
Project-URL: changelog, https://github.com/seapagan/fastapi-redis-cache-reborn/blob/main/CHANGELOG.md
